pykeyboard/README.md
pykeyboard/__init__.py
pykeyboard/inline_keyboard.py
pykeyboard/keyboard_base.py
pykeyboard/reply_keyboard.py
pyrogram_patch/README.md
pyrogram_patch/__init__.py
pyrogram_patch/dispatcher.py
pyrogram_patch/fsm/__init__.py
pyrogram_patch/fsm/base_storage.py
pyrogram_patch/fsm/filter.py
pyrogram_patch/fsm/states.py
pyrogram_patch/fsm/storages/__init__.py
pyrogram_patch/fsm/storages/memory_storage.py
pyrogram_patch/fsm/storages/redis_storage.py
pyrogram_patch/middlewares/__init__.py
pyrogram_patch/middlewares/middleware_types/__init__.py
pyrogram_patch/middlewares/middleware_types/middlewares.py
pyrogram_patch/patch.py
pyrogram_patch/patch_data_pool.py
pyrogram_patch/patch_helper.py
pyrogram_patch/router/__init__.py
pyrogram_patch/router/patched_decorators/__init__.py
pyrogram_patch/router/patched_decorators/on_callback_query.py
pyrogram_patch/router/patched_decorators/on_chat_join_request.py
pyrogram_patch/router/patched_decorators/on_chat_member_updated.py
pyrogram_patch/router/patched_decorators/on_chosen_inline_result.py
pyrogram_patch/router/patched_decorators/on_deleted_messages.py
pyrogram_patch/router/patched_decorators/on_disconnect.py
pyrogram_patch/router/patched_decorators/on_edited_message.py
pyrogram_patch/router/patched_decorators/on_inline_query.py
pyrogram_patch/router/patched_decorators/on_message.py
pyrogram_patch/router/patched_decorators/on_poll.py
pyrogram_patch/router/patched_decorators/on_raw_update.py
pyrogram_patch/router/patched_decorators/on_user_status.py
pyrogram_patch/router/router.py
kurigram_addons-0.1.4.dist-info/LICENSE
kurigram_addons-0.1.4.dist-info/METADATA
kurigram_addons-0.1.4.dist-info/WHEEL
kurigram_addons-0.1.4.dist-info/RECORD
