Metadata-Version: 2.1
Name: kurigram-addons
Version: 0.1.4
Summary: This package brings together several addons to kurigram including pykeyboard and FSM
License: MIT
Author: Johnnie
Author-email: 99084912+johnnie-610@users.noreply.github.com
Requires-Python: >=3.8,<4.0
Classifier: License :: OSI Approved :: MIT License
Classifier: Programming Language :: Python :: 3
Classifier: Programming Language :: Python :: 3.8
Classifier: Programming Language :: Python :: 3.9
Classifier: Programming Language :: Python :: 3.10
Classifier: Programming Language :: Python :: 3.11
Requires-Dist: kurigram (>=2.1.35,<3.0.0)
